nikippe
tests_unit
